satisfactory_calc/__init__.py
satisfactory_calc/define.py
satisfactory_calc/recipe.py
satisfactory_calc/sf_calc.py
satisfactory_calc-1.2.0.dist-info/LICENSE
satisfactory_calc-1.2.0.dist-info/METADATA
satisfactory_calc-1.2.0.dist-info/WHEEL
satisfactory_calc-1.2.0.dist-info/top_level.txt
satisfactory_calc-1.2.0.dist-info/RECORD
