Metadata-Version: 2.1
Name: satisfactory-calc
Version: 1.2.0
Summary: The satisfactory production line can be easily calculated.
Home-page: https://github.com/nicoyou/SatisfactoryCalc
Author: nicoyou
Author-email: nicoyou.info@gmail.com
License: MIT
Keywords: satisfactory-calc satisfactory calc game nicoyou
Platform: UNKNOWN
Classifier: Programming Language :: Python
Classifier: Programming Language :: Python :: 3
Classifier: Programming Language :: Python :: 3 :: Only
Classifier: Programming Language :: Python :: 3.10
Classifier: Programming Language :: Python :: 3.11
Classifier: Programming Language :: Python :: 3.12
License-File: LICENSE
Requires-Dist: nlib3
